{
    "Cbl-b": [
        "9FQH_D00.pdb",
        "9FQI_D01.pdb",
        "9FQJ_D02.pdb"
    ],
    "CHIP": [
        "9QEU_A90.pdb",
        "9QF1_A91.pdb",
        "9QFS_A87.pdb",
        "9QFY_A88.pdb",
        "9R1P_B07.pdb"
    ],
    "cIAP1": [
        "3MUP_SMK.pdb",
        "3OZ1_BMB.pdb",
        "3UW4_0DQ.pdb",
        "3UW4_CHG.pdb",
        "4HY4_1BG.pdb",
        "4HY5_1AQ.pdb",
        "4LGE_1Y0.pdb",
        "4LGU_1YH.pdb",
        "4MTI_2DX.pdb",
        "4MU7_2DY.pdb",
        "5M6N_7H9.pdb",
        "6EXW_C3K.pdb",
        "7TRM_IUN.pdb"
    ],
    "CRBN": [
        "4CI1_EF2.pdb",
        "4CI2_LVY.pdb",
        "4CI3_Y70.pdb",
        "4TZ4_LVY.pdb",
        "4TZC_EF2.pdb",
        "4TZU_Y70.pdb",
        "4V2Y_EF2.pdb",
        "4V2Z_Y70.pdb",
        "4V30_LVY.pdb",
        "4V31_DUR.pdb",
        "4V32_EF2.pdb",
        "5AMH_EF2.pdb",
        "5AMI_EF2.pdb",
        "5AMJ_EF2.pdb",
        "5FQD_LVY.pdb",
        "5HXB_85C.pdb",
        "5V3O_8W7.pdb",
        "5YIZ_EF2.pdb",
        "5YJ0_EF2.pdb",
        "5YJ1_6EL.pdb",
        "6H0F_Y70.pdb",
        "6H0G_Y70.pdb",
        "6R0Q_JNW.pdb",
        "6R0U_EF2.pdb",
        "6R0V_JO2.pdb",
        "6R11_JOB.pdb",
        "6R12_EF2.pdb",
        "6R13_EF2.pdb",
        "6R18_EF2.pdb",
        "6R19_EF2.pdb",
        "6R1A_EF2.pdb",
        "6R1C_EF2.pdb",
        "6R1D_JP5.pdb",
        "6R1K_JPB.pdb",
        "6R1W_EF2.pdb",
        "6R1X_JPQ.pdb",
        "6UML_Y70.pdb",
        "6XK9_V4M.pdb",
        "7BQU_EF2.pdb",
        "7BQV_F4U.pdb",
        "7LPS_RN9.pdb",
        "7PJK_7SE.pdb",
        "7PS9_8W7.pdb",
        "7PSO_835.pdb",
        "7PSO_EF2.pdb",
        "7SHH_9FT.pdb",
        "7U8F_LWK.pdb",
        "8AOP_MW6.pdb",
        "8AOQ_N8F.pdb",
        "8D7U_QFC.pdb",
        "8D7V_QFC.pdb",
        "8D7W_QFC.pdb",
        "8D7Z_QFC.pdb",
        "8D80_8W7.pdb",
        "8D81_Y70.pdb",
        "8DEY_LWK.pdb",
        "8G66_YOT.pdb",
        "8OIZ_Y70.pdb",
        "8OJH_VP9.pdb",
        "8OU3_EF2.pdb",
        "8OU4_W2F.pdb",
        "8OU5_W1X.pdb",
        "8OU6_W26.pdb",
        "8OU7_W1F.pdb",
        "8OU9_W1B.pdb",
        "8OUA_W0Z.pdb",
        "8RDP_A66.pdb",
        "8RDQ_YQO.pdb",
        "8RDR_A67.pdb",
        "8RDS_A65.pdb",
        "8RDT_A68.pdb",
        "8RQ8_QFC.pdb",
        "8RQ9_A79.pdb",
        "8RQA_LVY.pdb",
        "8RQC_QFC.pdb",
        "8TNP_Y70.pdb",
        "8TNQ_MIQ.pdb",
        "8TNR_MIQ.pdb",
        "8TZX_U3I.pdb",
        "8U15_8W7.pdb",
        "8U16_Y70.pdb",
        "8U17_Y70.pdb",
        "9CUO_E00.pdb",
        "9D0X_E01.pdb",
        "9DJT_E02.pdb",
        "9DJX_E04.pdb",
        "9DOM_E05.pdb",
        "9DQD_A40.pdb",
        "9DWV_A36.pdb",
        "9DWW_A37.pdb",
        "9E2U_RN9.pdb",
        "9FJX_LVY.pdb",
        "9GAO_A82.pdb",
        "9GJQ_A81.pdb",
        "9H59_A86.pdb",
        "9NFQ_A43.pdb",
        "9NFR_A39.pdb",
        "9NGT_A38.pdb",
        "9O91_A55.pdb",
        "9ODR_A53.pdb",
        "9ODS_A52.pdb",
        "9OHQ_A56.pdb",
        "9OHR_A57.pdb",
        "9Q03_A60.pdb",
        "9Q22_A54.pdb",
        "9Q2D_85C.pdb",
        "9SAF_B08.pdb",
        "9Y7D_E06.pdb"
    ],
    "DCAF1": [
        "7SSE_B1I.pdb",
        "7UFV_N6O.pdb",
        "8F8E_XJI.pdb",
        "8OG5_LQH_1.pdb",
        "8OG5_LQH_2.pdb",
        "8OG5_LQH_3.pdb",
        "8OG6_LQH_1.pdb",
        "8OG6_LQH_2.pdb",
        "8OG7_VMR.pdb",
        "8OG8_VM8_1.pdb",
        "8OG8_VM8_2.pdb",
        "8OG9_VM3_1.pdb",
        "8OG9_VM3_2.pdb",
        "8OGA_VLW.pdb",
        "8OGB_VN5.pdb",
        "8OGC_VMZ_1.pdb",
        "8OGC_VMZ_2.pdb",
        "8OO5_VUF_1.pdb",
        "8OO5_VUF_2.pdb",
        "9BHR_E07.pdb",
        "9BHS_E08.pdb",
        "9C1Q_E09.pdb",
        "9D4E_E10.pdb",
        "9PLY_A58.pdb",
        "9Y76_A59.pdb"
    ],
    "DCAF15": [
        "6PAI_O6M.pdb",
        "6Q0R_O6M.pdb",
        "6Q0V_P7M.pdb",
        "6Q0W_EF6.pdb",
        "6SJ7_EF6.pdb",
        "6UD7_EF6.pdb",
        "6UE5_Q5J.pdb",
        "8ROX_A71.pdb",
        "8ROY_A72.pdb"
    ],
    "DCAF16": [
        "8G46_YK3.pdb"
    ],
    "GID4": [
        "7SLZ_9QU.pdb"
    ],
    "HOIP(RNF31)": [
        "6GZY_FHH.pdb",
        "6KC5_D5U.pdb",
        "6KC6_D60.pdb"
    ],
    "HUWE1": [
        "8RD0_51X.pdb",
        "8RD1_YP2.pdb"
    ],
    "KEAP1": [
        "3VNG_FUU.pdb",
        "3VNH_FUU.pdb",
        "4CXT_SXJ.pdb",
        "4IFN_12O.pdb",
        "4IN4_4ID_1.pdb",
        "4IN4_4ID_2.pdb",
        "4IQK_IQK.pdb",
        "4L7C_1VW.pdb",
        "4L7D_1VX.pdb",
        "4N1B_2FS.pdb",
        "4XMB_41P.pdb",
        "4ZY3_K67.pdb",
        "5CGJ_51M.pdb",
        "5DAD_TX6.pdb",
        "5DAF_58E.pdb",
        "5FNQ_S0W.pdb",
        "5FNR_XMS.pdb",
        "5FNS_XYY.pdb",
        "5FNT_0PL.pdb",
        "5FNU_L6I.pdb",
        "5FZJ_75K.pdb",
        "5FZN_FB2.pdb",
        "5GIT_XXT.pdb",
        "6FFM_D8N.pdb",
        "6HWS_GX8.pdb",
        "6QMC_J6H.pdb",
        "6QMD_J6N_1.pdb",
        "6QMD_J6N_2.pdb",
        "6QME_J6Q.pdb",
        "6QMJ_J6K.pdb",
        "6QMK_J8H.pdb",
        "6SP1_LQ8.pdb",
        "6SP4_LQK.pdb",
        "6TYM_08A_1.pdb",
        "6TYM_08A_2.pdb",
        "6TYP_PKG.pdb",
        "6UF0_Q5V.pdb",
        "6V6Z_Q5Y.pdb",
        "6Z6A_Q9E.pdb",
        "6ZEX_QHN.pdb",
        "6ZEY_QGZ.pdb",
        "6ZEZ_QHH.pdb",
        "6ZF0_QHT.pdb",
        "6ZF1_QHK.pdb",
        "6ZF2_QJ5.pdb",
        "6ZF3_QH5.pdb",
        "6ZF4_QHW.pdb",
        "6ZF5_QH8.pdb",
        "6ZF6_QH2.pdb",
        "6ZF7_QHQ.pdb",
        "6ZF8_QHZ.pdb",
        "7OF8_VCQ.pdb",
        "7OF9_VBK.pdb",
        "7OFA_VBT.pdb",
        "7OFB_VCN.pdb",
        "7OFC_VCT.pdb",
        "7OFE_VBQ.pdb",
        "7OFF_VCB.pdb",
        "7P58_5UI.pdb",
        "7P5E_5VX.pdb",
        "7P5F_5QZ.pdb",
        "7P5I_5X9.pdb",
        "7P5K_5UZ.pdb",
        "7P5N_5RQ.pdb",
        "7P5P_5RB.pdb",
        "7Q5H_92I.pdb",
        "7Q6Q_8ZL.pdb",
        "7Q6S_91M.pdb",
        "7Q8R_9IB.pdb",
        "7Q96_9P0.pdb",
        "7XM2_GFD_1.pdb",
        "7XM2_GFD_2.pdb",
        "8A46_L5F.pdb",
        "8IVG_SGO.pdb",
        "8IVR_SIU.pdb",
        "8IXS_T6I.pdb",
        "8XGK_B13.pdb",
        "8XGV_B14.pdb",
        "9DU7_A41.pdb",
        "9ETX_A70.pdb",
        "9ETY_A69.pdb",
        "9F2P_A73.pdb",
        "9F2Q_A74.pdb",
        "9HWQ_B0A.pdb",
        "9HWR_A83.pdb",
        "9HWS_A85.pdb",
        "9HWT_A96.pdb",
        "9HWU_A92.pdb",
        "9HWV_A93.pdb",
        "9HWW_A94.pdb",
        "9HWX_A97.pdb",
        "9UO8_B15.pdb",
        "9VD2_B16.pdb"
    ],
    "LIVIN": [
        "2I3I_618.pdb",
        "3F7H_419.pdb",
        "3F7I_G13.pdb",
        "3GT9_516.pdb",
        "3GTA_851.pdb",
        "3UW5_0DQ.pdb",
        "3UW5_CHG.pdb"
    ],
    "MDM2": [
        "1RV1_IMZ_1.pdb",
        "1RV1_IMZ_2.pdb",
        "1T4E_DIZ.pdb",
        "1TTV_IMY.pdb",
        "2AXI_6CW.pdb",
        "2GV2_6CW.pdb",
        "2LZG_13Q.pdb",
        "2N06_44Z.pdb",
        "2N0U_48M.pdb",
        "2N0W_48L.pdb",
        "2N14_49H.pdb",
        "3FEA_6CW.pdb",
        "3FEA_PM3.pdb",
        "3IUX_HIA.pdb",
        "3JZK_YIN.pdb",
        "3LBJ_WW8_1.pdb",
        "3LBJ_WW8_2.pdb",
        "3LBK_K23.pdb",
        "3LBL_MI6.pdb",
        "3TJ2_TJ2.pdb",
        "3TU1_07G.pdb",
        "3U15_03M.pdb",
        "3VBG_03M.pdb",
        "3VZV_VZV.pdb",
        "3W69_LTZ.pdb",
        "4DIJ_BLF.pdb",
        "4ERE_0R2.pdb",
        "4ERF_0R3.pdb",
        "4HBM_0Y7.pdb",
        "4HG7_NUT.pdb",
        "4J3E_NUT.pdb",
        "4J74_I18_1.pdb",
        "4J74_I18_2.pdb",
        "4J7D_I31.pdb",
        "4J7E_I29.pdb",
        "4JRG_I09.pdb",
        "4JSC_1OY.pdb",
        "4JV7_1MN.pdb",
        "4JV9_1MO.pdb",
        "4JVE_1MQ.pdb",
        "4JVR_1MT.pdb",
        "4JWR_1MY.pdb",
        "4LWT_20Q.pdb",
        "4LWU_20U.pdb",
        "4LWV_20W.pdb",
        "4MDN_Y30.pdb",
        "4MDQ_28W_1.pdb",
        "4MDQ_28W_2.pdb",
        "4N5T_0EH.pdb",
        "4OAS_2SW.pdb",
        "4OBA_2TW.pdb",
        "4OCC_2TZ.pdb",
        "4ODE_2U0.pdb",
        "4ODF_2U1.pdb",
        "4OGN_2U5.pdb",
        "4OGT_2U6.pdb",
        "4OGV_2U7.pdb",
        "4OQ3_2V8.pdb",
        "4QO4_35S.pdb",
        "4QOC_35T.pdb",
        "4UMN_0EH.pdb",
        "4ZFI_4NJ.pdb",
        "4ZGK_4NX.pdb",
        "4ZYC_4SS.pdb",
        "4ZYF_4T4.pdb",
        "4ZYI_4TH.pdb",
        "5AFG_LAY.pdb",
        "5AFG_P07.pdb",
        "5C5A_NUT.pdb",
        "5J7F_6GG.pdb",
        "5J7G_6GG.pdb",
        "5LAV_6SK.pdb",
        "5LAW_6SJ.pdb",
        "5LAY_6SS.pdb",
        "5LAZ_6ST.pdb",
        "5LN2_6ZT.pdb",
        "5OAI_B5K.pdb",
        "5OC8_9QW.pdb",
        "5TRF_7HC.pdb",
        "5VK0_9E7.pdb",
        "5VK1_9E7.pdb",
        "5XXK_0EH.pdb",
        "5XXK_6CW.pdb",
        "5Z02_NUT.pdb",
        "5ZXF_NUT.pdb",
        "6AAW_0EH.pdb",
        "6GGN_EYH.pdb",
        "6H22_FL5.pdb",
        "6I3S_H28.pdb",
        "6KZU_E03.pdb",
        "6Q96_HRE.pdb",
        "6Q9H_HRH.pdb",
        "6Q9L_HTZ.pdb",
        "6Q9O_HU8.pdb",
        "6Q9Q_HUE.pdb",
        "6Q9U_HRE.pdb",
        "6Q9W_HRT.pdb",
        "6Q9Y_HRQ.pdb",
        "6V4E_0EH.pdb",
        "6V4G_0EH.pdb",
        "6Y4Q_O9E.pdb",
        "7BIR_TUZ.pdb",
        "7BIT_TV5.pdb",
        "7BIV_TUW.pdb",
        "7BJ0_TVH.pdb",
        "7BJ6_TVK.pdb",
        "7BMG_U3Z.pdb",
        "7C3Q_NUT.pdb",
        "7C3Y_NUT.pdb",
        "7C44_NUT.pdb",
        "7NA1_1GI.pdb",
        "7NA2_1I0.pdb",
        "7NA3_1I3.pdb",
        "7NA4_1I9.pdb",
        "7QDQ_AU0.pdb",
        "8AEU_M0L.pdb",
        "8GCG_FX9.pdb",
        "8GJS_0EH.pdb",
        "8HDG_NUT.pdb",
        "8IA5_NUT.pdb",
        "8PWC_G7I.pdb",
        "9GFK_B21_2.pdb"
    ],
    "MDMX": [
        "3LBJ_WW8.pdb",
        "7C3Q_NUT.pdb",
        "7C3Y_NUT.pdb",
        "7C44_NUT.pdb"
    ],
    "Parkin": [
        "8W31_D03.pdb"
    ],
    "RNF146": [
        "3V3L_V3L.pdb",
        "4QPL_V3L.pdb"
    ],
    "SOCS2": [
        "7ZLM_JIH.pdb",
        "7ZLN_JI9.pdb",
        "7ZLO_JI0.pdb",
        "7ZLP_JHR.pdb",
        "7ZLR_JH9.pdb",
        "7ZLS_JH9.pdb"
    ],
    "TRIM21": [
        "7HLA_A06_2.pdb",
        "7HLB_S9S.pdb",
        "7HLC_UWS.pdb",
        "7HLD_U0S.pdb",
        "7HLE_UXG.pdb",
        "7HLF_A18.pdb",
        "7HLG_A10.pdb",
        "7HLI_A12.pdb",
        "7HLJ_TU6.pdb",
        "7HLK_UUP.pdb",
        "7HLL_J4Q.pdb",
        "7HLN_E14.pdb",
        "7HLO_A02.pdb",
        "7HLP_A34_1.pdb",
        "7HLP_A34_2.pdb",
        "7HLQ_JMM.pdb",
        "7HLT_K1G_1.pdb",
        "7HLT_K1G_2.pdb",
        "7HLU_S0V_1.pdb",
        "7HLU_S0V_2.pdb",
        "7HLV_A28_2.pdb",
        "7HLW_A31.pdb",
        "7HLX_UXA.pdb",
        "7HM0_A09.pdb",
        "7HM1_VWV.pdb",
        "7HM2_NZJ.pdb",
        "7HM3_K6U.pdb",
        "7HM4_VW4.pdb",
        "7HM5_Q4L.pdb",
        "7HM6_A11.pdb",
        "7HM7_A08.pdb",
        "7HM8_UVA.pdb",
        "7HM9_A14.pdb",
        "7HMA_LV4.pdb",
        "7HMB_B1J.pdb",
        "7HMD_H04.pdb",
        "7HME_RXS.pdb",
        "7HMF_RZJ_1.pdb",
        "7HMF_RZJ_2.pdb",
        "7HMG_WKS.pdb",
        "7HMI_A07.pdb",
        "7HMJ_K1P.pdb",
        "7HMK_SFY.pdb",
        "7HMM_W0Y.pdb",
        "7HMO_O1M.pdb",
        "7HMP_ZQA_2.pdb",
        "7HMQ_E15.pdb",
        "7HMR_A03.pdb",
        "7HMS_T6J.pdb",
        "7HMT_A04.pdb",
        "7HMU_W1A.pdb",
        "7HMV_U2R.pdb",
        "7HMW_S7G.pdb",
        "7HMX_WJA.pdb",
        "7HMY_ZTQ.pdb",
        "7HMZ_A35.pdb",
        "7HN0_Q49.pdb",
        "7HN1_A13.pdb",
        "7HN2_A20.pdb",
        "7HN3_A01.pdb",
        "7HN4_VZY.pdb",
        "7HN5_JFM.pdb",
        "7HN6_A17.pdb",
        "7HN7_K2M.pdb",
        "7HN8_A23_1.pdb",
        "7HN8_A23_2.pdb",
        "7HN9_A26.pdb",
        "7HNA_WGM.pdb",
        "7HNB_T9Q.pdb",
        "7HNC_TV9.pdb",
        "7HNE_A24.pdb",
        "7HNF_A21.pdb",
        "7HNG_O3D.pdb",
        "7HNH_A16.pdb",
        "7HNI_NUA.pdb",
        "7HNJ_E16.pdb",
        "7HNK_WKG.pdb",
        "7HNL_RWS.pdb",
        "7HNM_A29.pdb",
        "7HNN_JGP.pdb",
        "7HNO_RV4.pdb",
        "7HNP_NUY.pdb",
        "7HNQ_GX4.pdb",
        "7HNR_NTV.pdb",
        "7HNS_LQP.pdb",
        "7HNU_GQJ.pdb",
        "7HNW_A30.pdb",
        "7HNX_WHP.pdb",
        "7HO0_E17.pdb",
        "7HO1_A25.pdb",
        "7HO3_A32.pdb",
        "7HO4_LL0.pdb",
        "7HO5_UXD.pdb",
        "7HO6_A15.pdb",
        "7HO7_JFP.pdb",
        "7HO8_O1J.pdb",
        "7HO9_E18.pdb",
        "7HOA_WNY.pdb",
        "8Y58_PMZ.pdb",
        "9EK5_A42.pdb",
        "9M3N_A61.pdb",
        "9Q9O_B00.pdb",
        "9Q9P_B01.pdb",
        "9Q9Q_A95.pdb",
        "9Q9R_B02.pdb",
        "9QBA_A89.pdb"
    ],
    "TRIM24": [
        "4YAB_4CN.pdb",
        "4YC9_4C1.pdb"
    ],
    "VHL": [
        "3ZRC_L8B_1.pdb",
        "3ZTC_TR0_1.pdb",
        "3ZTD_ZTD_1.pdb",
        "3ZUN_ZUN_1.pdb",
        "4AWJ_V6F_1.pdb",
        "4B95_UCK_1.pdb",
        "4B9K_TG0_1.pdb",
        "4BKS_X6C_1.pdb",
        "4BKT_QD0_1.pdb",
        "4W9C_3JG_1.pdb",
        "4W9D_3JK_1.pdb",
        "4W9E_3JT_1.pdb",
        "4W9F_3JU_1.pdb",
        "4W9G_3JV_1.pdb",
        "4W9H_3JF_1.pdb",
        "4W9I_3JS_1.pdb",
        "4W9J_3JH_1.pdb",
        "4W9K_3JO_1.pdb",
        "4W9L_3JJ_1.pdb",
        "5LLI_6Z3_1.pdb",
        "5NVV_9BT_1.pdb",
        "5NVW_9BW_1.pdb",
        "5NVX_4YY_1.pdb",
        "5NVY_9B5_1.pdb",
        "5NVZ_9BN_1.pdb",
        "5NW0_9BK_1.pdb",
        "5NW1_9BH_1.pdb",
        "5NW2_9B8_1.pdb",
        "6FMI_DV2_1.pdb",
        "6FMJ_DV5_1.pdb",
        "6FMK_DV8_1.pdb",
        "6GFY_EXH_1.pdb",
        "6GFZ_EXE_1.pdb",
        "6GMR_F4K.pdb",
        "8BDI_QF7_1.pdb",
        "8BDJ_QE0_1.pdb",
        "8BDL_QF3_1.pdb",
        "8BDM_QE9_1.pdb",
        "8BDN_QFR_1.pdb",
        "8BDO_QFF_1.pdb",
        "8CQE_VFO_1.pdb",
        "8CQK_VYQ_1.pdb",
        "8CQL_VH3_1.pdb",
        "8P0F_WBN_1.pdb",
        "8QCU_REI.pdb",
        "8QCU_VHL_1.pdb",
        "8QJS_VL6_1.pdb",
        "8VLB_3JF.pdb",
        "9BOL_E19.pdb",
        "9EQJ_A77_1.pdb",
        "9EQM_A78.pdb",
        "9F1M_A75_1.pdb",
        "9F1N_A76_1.pdb",
        "9GHX_REI.pdb",
        "9GHX_VHL_1.pdb",
        "9GIO_A84.pdb",
        "9OIO_A51_1.pdb",
        "9QE4_A99_1.pdb",
        "9QE5_A98_1.pdb"
    ],
    "XIAP": [
        "1TFQ_998.pdb",
        "1TFT_997.pdb",
        "2JK7_BI6.pdb",
        "2OPY_CO9.pdb",
        "3CLX_X22.pdb",
        "3CM2_X23.pdb",
        "3CM7_X22.pdb",
        "3EYL_SMK.pdb",
        "3HL5_9JZ.pdb",
        "4HY0_1AQ.pdb",
        "4KJU_1RH.pdb",
        "4KJV_1RK.pdb",
        "4WVS_4LZ.pdb",
        "4WVU_3V8.pdb",
        "4WVU_HOX.pdb",
        "5C0K_4WK.pdb",
        "5C0L_4WJ.pdb",
        "5C3H_4XE.pdb",
        "5C3K_4XF.pdb",
        "5C7A_4YE.pdb",
        "5C7B_4YD.pdb",
        "5C7C_4YC.pdb",
        "5C7D_4YF.pdb",
        "5C83_4YN.pdb",
        "5C84_4YL.pdb",
        "5M6E_7HT.pdb",
        "5M6F_7HU.pdb",
        "5M6H_7J6.pdb",
        "5M6L_7H9.pdb",
        "5M6M_7H8.pdb",
        "5OQW_A4E.pdb",
        "6EY2_C3T.pdb",
        "6H6Q_FUK.pdb",
        "6H6R_FUE.pdb",
        "8GH7_7PE.pdb",
        "8GH7_CHG.pdb",
        "8GH7_ZHW.pdb"
    ]
}
